Metadata-Version: 2.4
Name: iflow-mcp_sonos-mcp-server
Version: 0.1.0
Summary: Add your description here
Requires-Python: >=3.13
Requires-Dist: mcp[cli]>=1.5.0
Requires-Dist: soco>=0.30.9
